{"name":"P3-OpenFN-RetailPayments","intents":[{"intent":"change","examples":[{"text":"update memo"},{"text":"provide a memo as"},{"text":"make it"},{"text":"change the memo"},{"text":"change the comment as"},{"text":"change the amount"},{"text":"change memo to"},{"text":"can you update the memo"},{"text":"can you update the amount"},{"text":"update the"},{"text":"add a memo as"},{"text":"add a comment"},{"text":"update to"},{"text":"update the memo as"},{"text":"update the comment to"},{"text":"update the amount to"}],"description":null},{"intent":"greetings","examples":[{"text":"Hello Watson"},{"text":"hey"},{"text":"yo"},{"text":"yello"},{"text":"namaste"},{"text":"Its not that good"},{"text":"I'm feeling good thanks"},{"text":"I am not feeling good"},{"text":"howdy"},{"text":"How are you doing"},{"text":"hola como estas"},{"text":"Hola"},{"text":"hiya"},{"text":"Hi watson"},{"text":"hi there"},{"text":"hi how are u"},{"text":"hey there"},{"text":"heya"},{"text":"hi"},{"text":"aloha"},{"text":"bad"},{"text":"bonjour"},{"text":"buenos dias"},{"text":"ciao"},{"text":"feeling bit low"},{"text":"g'day"},{"text":"good"},{"text":"good day"},{"text":"good evening"},{"text":"good how are you"},{"text":"good morning"},{"text":"greetings"},{"text":"Hello"},{"text":"Hello, how are you"}],"description":null},{"intent":"sendMoney","examples":[{"text":"I want to pay"},{"text":"make a payment"},{"text":"send"},{"text":"send $100"},{"text":"send $100 to John Smith"},{"text":"send a payment of to"},{"text":"send money to"},{"text":"sent"},{"text":"sent to"},{"text":"transfer funds to"},{"text":"transfer money to"},{"text":"transfer to"},{"text":"can you pay"},{"text":"I need to pay"},{"text":"I would like to pay"}],"description":null},{"intent":"callMe","examples":[{"text":"can you call me"},{"text":"call me"},{"text":"refer to me as"},{"text":"my name is"},{"text":"change my name to"}],"description":null},{"intent":"balance","examples":[{"text":"account information"},{"text":"what is my account balance"},{"text":"show me my balance"},{"text":"list my accounts"},{"text":"show me accounts"},{"text":"how much money do i have"},{"text":"check my balance"},{"text":"what is the balance on my account"},{"text":"balance please"}],"description":null},{"intent":"goodbyes","examples":[{"text":"thank you"},{"text":"toodles"},{"text":"then bye"},{"text":"that will be all"},{"text":"that's great"},{"text":"that's all for now"},{"text":"that is all i had"},{"text":"thanks watson"},{"text":"sounds good"},{"text":"soon"},{"text":"so long"},{"text":"signing out"},{"text":"signing off"},{"text":"should go"},{"text":"should be going"},{"text":"see you"},{"text":"see ya soon"},{"text":"see ya later"},{"text":"see ya"},{"text":"run"},{"text":"over and out"},{"text":"out of time"},{"text":"ok bye"},{"text":"my time is up"},{"text":"logging off"},{"text":"leave"},{"text":"laters"},{"text":"later"},{"text":"I'm leaving"},{"text":"i am done"},{"text":"gtg"},{"text":"gotta run"},{"text":"gotta go"},{"text":"good night"},{"text":"good day"},{"text":"good bye"},{"text":"goodbye"},{"text":"go"},{"text":"farewell"},{"text":"cya"},{"text":"bye now"},{"text":"bye bye"},{"text":"bye"},{"text":"au revoir"},{"text":"adios"},{"text":"adieu"}],"description":null},{"intent":"viewTransactions","examples":[{"text":"show me payments made in the last month"},{"text":"show me payment transactions"},{"text":"show me recent transactions"},{"text":"show me the payments I have received in the past"},{"text":"what payments have been sent and received last week"},{"text":"can i see all payments"},{"text":"list my recent payments"},{"text":"show me all payments in the past month"}],"description":null},{"intent":"cancel","examples":[{"text":"i want to do something else"},{"text":"get me out of here"},{"text":"forget that"},{"text":"exit"},{"text":"don't do that"},{"text":"can we begin again"},{"text":"i want to cancel"},{"text":"cancel that"},{"text":"ignore the previous request"},{"text":"ignore that"},{"text":"i do not want to proceed with that"},{"text":"start over"},{"text":"reset"},{"text":"let's start again"},{"text":"go to the start"}],"description":null},{"intent":"off_topic","examples":[{"text":"What's the speed"},{"text":"what kind of food do you eat"},{"text":"what is your name"},{"text":"what is my speed"},{"text":"Turn left"},{"text":"This is good"},{"text":"This is awesome"},{"text":"testing om"},{"text":"test"},{"text":"tell me your favorite foods"},{"text":"tell me your favorite color"},{"text":"tell me some jokes"},{"text":"tell me jokes"},{"text":"tell me joke"},{"text":"tell me a joke"},{"text":"system error, unable to lonin"},{"text":"sup"},{"text":"shut down"},{"text":"shutdown"},{"text":"roll down windows"},{"text":"repair my car"},{"text":"Post-it notes taste terrible."},{"text":"poop"},{"text":"open door"},{"text":"Nuts"},{"text":"nope"},{"text":"near"},{"text":"make me a sandwich"},{"text":"lgits"},{"text":"lgiths"},{"text":"know any jokes"},{"text":"I want to talk"},{"text":"i want to see how this demo works"},{"text":"I want to eat tacos everyday"},{"text":"I want to date you"},{"text":"i want jokes"},{"text":"it's too dark"},{"text":"I need to shut it down"},{"text":"i need a new wheelchair"},{"text":"I love spicy food"},{"text":"I love dolphins"},{"text":"I enjoy petting cats"},{"text":"I'd like to have dinner with you"},{"text":"huhu"},{"text":"how tall are you"},{"text":"how old are you"},{"text":"how much do you weigh"},{"text":"how many licks does it take to get to the center of a tootsie roll"},{"text":"how far to"},{"text":"how far is the moon"},{"text":"how far is"},{"text":"how close is"},{"text":"hot"},{"text":"go fast"},{"text":"funny"},{"text":"fdsafsaHi watson"},{"text":"do you love"},{"text":"Do you like"},{"text":"do you hate"},{"text":"don't you know any jokes"},{"text":"dfddfg"},{"text":"deploy airbags"},{"text":"culd"},{"text":"cool"},{"text":"cold"},{"text":"cats are my favorite animal"},{"text":"carrot"},{"text":"book a flight for NY on sunday"},{"text":"asdasidjiwe"},{"text":"asdasdasda"},{"text":"aho"},{"text":"go slow"},{"text":"You're asking me too much"},{"text":"you are funny"},{"text":"Yolo"},{"text":"yes"},{"text":"yeah"},{"text":"why is the sky blue"},{"text":"why"},{"text":"which color is best for wedding"},{"text":"where should I turn"},{"text":"where is the poop deck on this ship"},{"text":"Where are we"},{"text":"when will it be funny?"},{"text":"what types of food do you like"},{"text":"what time is it"},{"text":"whats your name"},{"text":"what's your name"},{"text":"whats your favorite movie"},{"text":"whats your favorite color"},{"text":"what's your favorite"},{"text":"what's your"},{"text":"what's up"},{"text":"whats the square root of 70"}],"description":null},{"intent":"capabilities","examples":[{"text":"How are you going to help me"},{"text":"what things can you do"},{"text":"what else"},{"text":"what do you know"},{"text":"what do i say"},{"text":"what can you do"},{"text":"What can i say"},{"text":"what are your capabilities Watson"},{"text":"what are you capable of"},{"text":"tell me what you can do"},{"text":"tell me what things you can do"},{"text":"I don't know"},{"text":"how do i"},{"text":"how can you help me"},{"text":"how can i provide"},{"text":"help me out"},{"text":"why should i use you"}],"description":null},{"intent":"receiveMoney","examples":[{"text":"i would like to receive money from"},{"text":"i need to receive money from someone"},{"text":"i need to get money from"},{"text":"i am yet to get cash from"},{"text":"can you request for"},{"text":"ask someone for a payment"},{"text":"ask for money"},{"text":"make a request for from"},{"text":"owe's me money for"},{"text":"receive a payment"},{"text":"receive from"},{"text":"receive money from"},{"text":"request $100 from John Smith"},{"text":"i would like to request from"}],"description":null}],"entities":[{"entity":"category","values":[{"type":"synonyms","value":"payment","metadata":null,"synonyms":["payments"]},{"type":"synonyms","value":"utility","metadata":null,"synonyms":["electricity","energy","power"]},{"type":"synonyms","value":"travel","metadata":null,"synonyms":[]},{"type":"synonyms","value":"fuel","metadata":null,"synonyms":["gas"]},{"type":"synonyms","value":"grocery","metadata":null,"synonyms":[]},{"type":"synonyms","value":"dining","metadata":null,"synonyms":["dinner","eating","eating out","lunch","restaurant"]},{"type":"synonyms","value":"fee","metadata":null,"synonyms":["fees"]}],"metadata":null,"description":null},{"entity":"acknowledge","values":[{"type":"synonyms","value":"no","metadata":null,"synonyms":["cancel","forget it","forget that","go back","ignore","na","nada","nay","neah","negative","nope","not"]},{"type":"synonyms","value":"yes","metadata":null,"synonyms":["absolutely","correct","go ahead","perfect","proceed","right","roger","sure","ya","yeah","yep","yup"]}],"metadata":null,"description":null},{"entity":"thank","values":[{"type":"synonyms","value":"thank you","metadata":null,"synonyms":["thank","thanks","that was helpful"]}],"metadata":null,"description":null},{"entity":"type","values":[{"type":"synonyms","value":"debit","metadata":null,"synonyms":["debit","debits","outgoing","sent"]},{"type":"synonyms","value":"credit","metadata":null,"synonyms":["credit","credited","credits","receive","received"]}],"metadata":null,"description":null},{"entity":"sys-currency","values":[],"metadata":null,"description":null},{"entity":"sendMoneyTo","values":[],"metadata":null,"description":null},{"entity":"sys-number","values":[],"metadata":null,"description":null},{"entity":"sys-percentage","values":[],"metadata":null,"description":null},{"entity":"receiveMoneyFrom","values":[],"metadata":null,"description":null},{"entity":"sys-person","values":[],"metadata":null,"description":null}],"language":"en","metadata":{"api_version":{"major_version":"v1","minor_version":"2017-05-26"},"runtime_version":"2016-09-20"},"description":"Retail Payments Use Cases","dialog_nodes":[{"type":"standard","title":null,"output":{"text":"Hi, how can I help you today?"},"parent":"node_1_1478122044203","context":{"defaultCounter":0},"metadata":null,"next_step":null,"conditions":"true","description":null,"dialog_node":"node_4_1478122444272","previous_sibling":"node_3_1478122398986"},{"type":"standard","title":null,"output":{"text":{"append":true,"values":["Hi <? $person.fname ?>, how can I help you today?","Hello <? $person.fname ?>, how can I help you today?"],"selection_policy":"random"}},"parent":"node_1_1478122044203","context":{"defaultCounter":0},"metadata":null,"next_step":null,"conditions":"$person && $person.fname","description":null,"dialog_node":"node_3_1478122398986","previous_sibling":null},{"type":"standard","title":null,"output":{},"parent":"node_5_1478722896603","context":null,"metadata":null,"next_step":{"behavior":"jump_to","selector":"condition","dialog_node":"node_5_1478722896603"},"conditions":"true","description":null,"dialog_node":"node_6_1478724492979","previous_sibling":"node_5_1478724240545"},{"type":"standard","title":null,"output":{"text":"How much would you like to receive from <? $result.contacts.get(0).fname ?> <? $result.contacts.get(0).lname ?>?"},"parent":"node_5_1478722896603","context":null,"metadata":null,"next_step":{"behavior":"jump_to","selector":"user_input","dialog_node":"node_3_1478723709214"},"conditions":"! @sys-number && ! #cancel","description":null,"dialog_node":"node_4_1478723947460","previous_sibling":"node_3_1478723709214"},{"type":"standard","title":null,"output":{"text":"Okay, cancelled. Is there something else I can help with?"},"parent":"node_5_1478722896603","context":null,"metadata":null,"next_step":null,"conditions":"#cancel && intents[0].confidence >= 0.60","description":null,"dialog_node":"node_5_1478724240545","previous_sibling":"node_4_1478723947460"},{"type":"standard","title":null,"output":{},"parent":"node_5_1478722896603","context":{"amount":"<? @sys-number ?>"},"metadata":null,"next_step":{"behavior":"jump_to","selector":"condition","dialog_node":"node_5_1478722896603"},"conditions":"entities['sys-number']?.value","description":null,"dialog_node":"node_3_1478723709214","previous_sibling":null},{"type":"standard","title":null,"output":{"text":"You have <? $result.type ?> <? $result.transactions.length ?> <? @category ?> transactions totaling <? $result.total ?>"},"parent":"node_5_1478122605834","context":{"action":{"display":"transactions"}},"metadata":null,"next_step":null,"conditions":"$result && $result.transactions.length>0 && @type","description":null,"dialog_node":"node_3_1478298660651","previous_sibling":"node_5_1478278775394"},{"type":"standard","title":null,"output":{"text":"You have <? $result.transactions.length ?> <? @category ?> transactions totaling <? $result.total ?>"},"parent":"node_5_1478122605834","context":{"action":{"display":"transactions"}},"metadata":null,"next_step":null,"conditions":"$result && $result.total && $result.transactions.length > 0","description":null,"dialog_node":"node_2_1478298493000","previous_sibling":"node_8_1478283814515"},{"type":"standard","title":null,"output":{"text":"You have <? $result.transactions.length ?> <? @category ?> transactions totaling <? $result.total ?>."},"parent":"node_5_1478122605834","context":{"action":{"display":"transactions"}},"metadata":null,"next_step":null,"conditions":"$result && $result.total && $result.transactions.length > 0 && $alchemy_language.dates.length > 0","description":null,"dialog_node":"node_8_1478283814515","previous_sibling":"node_3_1478298660651"},{"type":"standard","title":null,"output":{"text":"There were no transactions found on your accounts for this search criteria."},"parent":"node_5_1478122605834","context":null,"metadata":null,"next_step":null,"conditions":"true","description":null,"dialog_node":"node_7_1478282336996","previous_sibling":"node_2_1478298493000"},{"type":"standard","title":null,"output":{"text":"You have <? $result.type ?> <? $result.transactions.length ?> <? @category ?> transactions totaling <? $result.total ?> since <? $alchemy_language.dates.get(0).formattedDate ?>"},"parent":"node_5_1478122605834","context":{"action":{"display":"transactions"}},"metadata":null,"next_step":null,"conditions":"$result && $result.total && $result.transactions.length > 0 && @type && $alchemy_language.dates.length > 0","description":null,"dialog_node":"node_5_1478278775394","previous_sibling":null},{"type":"standard","title":null,"output":{"text":{"append":true,"values":["I found a contact named <? $result.contacts.get(0).fname ?> <? $result.contacts.get(0).lname ?>. Is this the contact you want to receive $<? $amount?> from?","Please confirm the request of $<? $amount?> from <? $result.contacts.get(0).fname ?> <? $result.contacts.get(0).lname ?>.","Please verify the request for $<? $amount?> from <? $result.contacts.get(0).fname ?> <? $result.contacts.get(0).lname ?>.","Shall I submit a request for $<? $amount?> to <? $result.contacts.get(0).fname ?> <? $result.contacts.get(0).lname ?>."],"selection_policy":"sequential"}},"parent":"node_3_1478720389276","context":{"action":{"display":"transaction_confirmation","payment_type":"receive"},"result":{"amount":"<? $amount ?>","comment":"<?  $payment_reason ? $payment_reason : '' ?>","contact_fname":"<? $result.contacts.get(0).fname ?>","contact_lname":"<? $result.contacts.get(0).lname ?>","contact_phone":"<? $result.contacts.get(0).phone ?>"}},"metadata":null,"next_step":null,"conditions":"$result && $result.contacts.length>0 && $amount","description":null,"dialog_node":"node_1_1478723346338","previous_sibling":"node_5_1478722896603"},{"type":"standard","title":null,"output":{"text":"I did not find a contact with that name."},"parent":"node_3_1478720389276","context":null,"metadata":null,"next_step":null,"conditions":"! $result || ! $result.contacts || $result.contacts?.length == 0","description":null,"dialog_node":"node_2_1478723507432","previous_sibling":"node_1_1478723346338"},{"type":"standard","title":null,"output":{"text":{"append":true,"values":["How much would you like to request?","What amount do you want to request?"],"selection_policy":"random"}},"parent":"node_3_1478720389276","context":null,"metadata":null,"next_step":null,"conditions":"$result && $result.contacts.length>0 && ! $amount","description":null,"dialog_node":"node_5_1478722896603","previous_sibling":null},{"type":"standard","title":null,"output":{"text":"How much would you like to send <? $result.contacts.get(0).fname ?> <? $result.contacts.get(0).lname ?>?"},"parent":"node_2_1478553604690","context":null,"metadata":null,"next_step":{"behavior":"jump_to","selector":"user_input","dialog_node":"node_3_1478554110727"},"conditions":"!@sys-number && !#cancel","description":null,"dialog_node":"node_4_1478554136459","previous_sibling":"node_3_1478554110727"},{"type":"standard","title":null,"output":{"text":"Okay, cancelled. Is there anything else I can help you with?"},"parent":"node_2_1478553604690","context":null,"metadata":null,"next_step":null,"conditions":"#cancel && intents[0].confidence >= 0.60","description":null,"dialog_node":"node_7_1478555395356","previous_sibling":"node_4_1478554136459"},{"type":"standard","title":null,"output":{},"parent":"node_2_1478553604690","context":null,"metadata":null,"next_step":{"behavior":"jump_to","selector":"condition","dialog_node":"node_2_1478553604690"},"conditions":"true","description":null,"dialog_node":"node_1_1478706484706","previous_sibling":"node_7_1478555395356"},{"type":"standard","title":null,"output":{},"parent":"node_2_1478553604690","context":{"amount":"<? @sys-number ?>"},"metadata":null,"next_step":{"behavior":"jump_to","selector":"condition","dialog_node":"node_1_1478552078118"},"conditions":"entities['sys-number']?.value","description":null,"dialog_node":"node_3_1478554110727","previous_sibling":null},{"type":"standard","title":null,"output":{"text":"I'm not sure about that. You can say things like \"Send 100 dollars to John Smith for the movie tickets\",  \"Show me payments\"."},"parent":"node_2_1478122055040","context":null,"metadata":null,"next_step":null,"conditions":"true","description":null,"dialog_node":"node_5_1479165410566","previous_sibling":"node_4_1479165361410"},{"type":"standard","title":null,"output":{"text":"I am having trouble understanding you. Try asking your question in a different way."},"parent":"node_2_1478122055040","context":{"defaultCounter":0},"metadata":null,"next_step":null,"conditions":"$defaultCounter>2","description":null,"dialog_node":"node_4_1479165361410","previous_sibling":null},{"type":"standard","title":null,"output":{"text":{"append":true,"values":["Whom do you want to receive money from?","I'm having trouble identifying your contact to request money. You can say things like 'I want to receive $50 from John Smith.'","<? $person.fname ?>, please provide a recipient name to request the money.","Who is the contact you would like to receive money from?"],"selection_policy":"sequential"}},"parent":"node_1_1478720291899","context":null,"metadata":null,"next_step":{"behavior":"jump_to","selector":"user_input","dialog_node":"node_2_1478720352247"},"conditions":"true","description":null,"dialog_node":"node_4_1478720780643","previous_sibling":"node_3_1478720389276"},{"type":"standard","title":null,"output":{},"parent":"node_1_1478720291899","context":{"action":{"lookup":"contacts","search":{"name":"<? $alchemy_language.entities.get(0).text ?>","input":"<? input.text ?>"}},"amount":"<? @sys-number  ? @sys-number : $amount ?>"},"metadata":null,"next_step":null,"conditions":"$alchemy_language && $alchemy_language.entities.length>0 && $alchemy_language.entities.get(0).text","description":null,"dialog_node":"node_3_1478720389276","previous_sibling":"node_2_1478720352247"},{"type":"standard","title":null,"output":{"text":"Okay, I have cancelled that request. What else can I help you with?"},"parent":"node_1_1478720291899","context":null,"metadata":null,"next_step":null,"conditions":"#cancel && intents[0].confidence > 0.60","description":null,"dialog_node":"node_2_1478720352247","previous_sibling":null},{"type":"standard","title":null,"output":{},"parent":"node_1_1478552078118","context":{"amount":{},"result":{}},"metadata":null,"next_step":{"behavior":"jump_to","selector":"condition","dialog_node":"node_9_1478557521266"},"conditions":"true","description":null,"dialog_node":"node_12_1478558112516","previous_sibling":"node_1_1479333493153"},{"type":"standard","title":null,"output":{},"parent":"node_1_1478552078118","context":{"amount":"<? @sys-number? @sys-number : $amount ?>","payment_reason":"<? input.text.extract('(for|regarding|as|to).*',0).replaceFirst('^\\S+\\s+', '') ?>"},"metadata":null,"next_step":{"behavior":"jump_to","selector":"condition","dialog_node":"node_1_1478552078118"},"conditions":"#change && intents[0].confidence >= 0.80","description":null,"dialog_node":"node_1_1479333493153","previous_sibling":"node_11_1478558068261"},{"type":"standard","title":null,"output":{"text":{"values":["All right, I will cancel this transaction. Is there anything else I can help you with <? $person.fname ?>?"]}},"parent":"node_1_1478552078118","context":{"amount":{},"result":{}},"metadata":null,"next_step":null,"conditions":"@acknowledge:no","description":null,"dialog_node":"node_11_1478558068261","previous_sibling":"node_10_1478557951266"},{"type":"standard","title":null,"output":{},"parent":"node_1_1478552078118","context":{"action":{"data":{"amount":"<? $amount ?>","comment":"<?  $payment_reason ? $payment_reason : '' ?>","contact_fname":"<? $result.contacts.get(0).fname ?>","contact_lname":"<? $result.contacts.get(0).lname ?>","contact_phone":"<? $result.contacts.get(0).phone ?>"},"update":"send_payment"}},"metadata":null,"next_step":null,"conditions":"@acknowledge:yes","description":null,"dialog_node":"node_10_1478557951266","previous_sibling":null},{"type":"standard","title":null,"output":{"text":{"append":true,"values":["I found a contact named <? $result.contacts.get(0).fname ?> <? $result.contacts.get(0).lname ?>. Is this the contact you want to pay $<? $amount?> to?","Please confirm the payment of $<? $amount?> to <? $result.contacts.get(0).fname ?> <? $result.contacts.get(0).lname ?>.","Please verify the payment of $<? $amount?> to <? $result.contacts.get(0).fname ?> <? $result.contacts.get(0).lname ?>.","Shall I submit the payment of $<? $amount?> to <? $result.contacts.get(0).fname ?> <? $result.contacts.get(0).lname ?>."],"selection_policy":"sequential"}},"parent":"node_2_1478537424848","context":{"action":{"display":"transaction_confirmation","payment_type":"send"},"result":{"amount":"<? $amount ?>","comment":"<?  $payment_reason ? $payment_reason : '' ?>","contact_fname":"<? $result.contacts.get(0).fname ?>","contact_lname":"<? $result.contacts.get(0).lname ?>","contact_phone":"<? $result.contacts.get(0).phone ?>"}},"metadata":null,"next_step":null,"conditions":"$result && $result.contacts.length>0 && $amount","description":null,"dialog_node":"node_1_1478552078118","previous_sibling":"node_5_1478901623348"},{"type":"standard","title":null,"output":{"text":{"append":true,"values":["Sorry $person.fname, your <? $account.type ?> account balance of <? $account.formattedBalance ?> is insufficient to complete this transfer.","Unfortunately, your <? $account.type ?> account balance of <? $account.formattedBalance ?> is insufficient to complete this transfer."],"selection_policy":"sequential"}},"parent":"node_2_1478537424848","context":null,"metadata":null,"next_step":null,"conditions":"$amount && $account && $amount>$account.balance","description":null,"dialog_node":"node_5_1478901623348","previous_sibling":"node_2_1478553604690"},{"type":"standard","title":null,"output":{"text":"I did not find a contact with that name."},"parent":"node_2_1478537424848","context":null,"metadata":null,"next_step":null,"conditions":"! $result || ! $result.contacts || $result.contacts?.length == 0","description":null,"dialog_node":"node_6_1478554591073","previous_sibling":"node_1_1478552078118"},{"type":"standard","title":null,"output":{"text":{"append":true,"values":["How much would you like to send?","How much do you want to send?"],"selection_policy":"random"}},"parent":"node_2_1478537424848","context":null,"metadata":null,"next_step":null,"conditions":"$result && $result.contacts.length && !$amount","description":null,"dialog_node":"node_2_1478553604690","previous_sibling":null},{"type":"standard","title":"Submit_Payment","output":{"text":"$<? $amount ?> has been sent and is available for <? $result.contacts.get(0).fname ?> <? $result.contacts.get(0).lname ?> to use."},"parent":"node_10_1478557951266","context":null,"metadata":null,"next_step":null,"conditions":"true","description":null,"dialog_node":"Submit_Payment","previous_sibling":null},{"type":"standard","title":null,"output":{},"parent":"node_1_1478882289339","context":{"action":{"lookup":"accounts"}},"metadata":null,"next_step":{"behavior":"jump_to","selector":"condition","dialog_node":"node_4_1478900017327"},"conditions":"true","description":null,"dialog_node":"node_2_1478882893858","previous_sibling":"node_4_1478900017327"},{"type":"standard","title":null,"output":{"text":{"append":true,"values":["Your <? $account.type ?> account balance is <? $account.formattedBalance ?>.","You have <? $account.formattedBalance ?> available in your <? $account.type ?> account.","The available balance in your <? $account.type ?> account is <? $account.formattedBalance ?>."],"selection_policy":"random"}},"parent":"node_1_1478882289339","context":null,"metadata":null,"next_step":null,"conditions":"$account","description":null,"dialog_node":"node_4_1478900017327","previous_sibling":null},{"type":"standard","title":null,"output":{},"parent":"node_1_1478537303868","context":{"action":{"lookup":"contacts","search":{"name":"<? $alchemy_language.entities.get(0).text ?>","input":"<? input.text ?>"}},"amount":"<? @sys-number  ? @sys-number : $amount ?>"},"metadata":{},"next_step":null,"conditions":"$alchemy_language && $alchemy_language.entities.length && $alchemy_language.entities.get(0)","description":null,"dialog_node":"node_2_1478537424848","previous_sibling":"node_8_1478555630578"},{"type":"standard","title":null,"output":{"text":{"append":true,"values":["Whom would you like to pay?","Whom do you want to send money to?","Do you have a recipient name to receive the money. You can say things like 'I want to pay John Smith $50.'"],"selection_policy":"sequential"}},"parent":"node_1_1478537303868","context":null,"metadata":null,"next_step":{"behavior":"jump_to","selector":"user_input","dialog_node":"node_8_1478555630578"},"conditions":"true","description":null,"dialog_node":"node_3_1478537785706","previous_sibling":"node_2_1478537424848"},{"type":"standard","title":null,"output":{"text":"Okay, cancelled. Is there anything else can I help you with?"},"parent":"node_1_1478537303868","context":null,"metadata":null,"next_step":null,"conditions":"#cancel && intents[0].confidence > 0.60","description":null,"dialog_node":"node_8_1478555630578","previous_sibling":null},{"type":"standard","title":null,"output":{},"parent":"node_1_1478723346338","context":{"amount":"<? @sys-number? @sys-number : $amount ?>","payment_reason":"<? input.text.extract('(for|regarding|as|to).*',0).replaceFirst('^\\S+\\s+', '') ?>"},"metadata":null,"next_step":{"behavior":"jump_to","selector":"condition","dialog_node":"node_1_1478723346338"},"conditions":"#change && intents[0].confidence >= 0.80","description":null,"dialog_node":"node_2_1479334594427","previous_sibling":"node_8_1478725235291"},{"type":"standard","title":null,"output":{},"parent":"node_1_1478723346338","context":{"amount":{},"result":{}},"metadata":null,"next_step":{"behavior":"jump_to","selector":"condition","dialog_node":"node_2_1478720352247"},"conditions":"true","description":null,"dialog_node":"node_9_1478725426595","previous_sibling":"node_2_1479334594427"},{"type":"standard","title":null,"output":{"text":"All right, I will cancel this transaction. Is there anything else I can help you with <? $person.fname ?>?"},"parent":"node_1_1478723346338","context":{"amount":{},"result":{}},"metadata":null,"next_step":null,"conditions":"@acknowledge:no","description":null,"dialog_node":"node_8_1478725235291","previous_sibling":"node_7_1478725078058"},{"type":"standard","title":null,"output":{"text":"Okay, I have sent <? $result.contacts.get(0).fname ?> <? $result.contacts.get(0).lname ?> a payment request of $<? $amount ?>."},"parent":"node_1_1478723346338","context":null,"metadata":null,"next_step":null,"conditions":"@acknowledge:yes","description":null,"dialog_node":"node_7_1478725078058","previous_sibling":null},{"type":"standard","title":null,"output":{"text":"I did not receive an input statement."},"parent":null,"context":null,"metadata":null,"next_step":null,"conditions":"input && input.text == '' || input.text == ' '","description":null,"dialog_node":"node_1_1479401108377","previous_sibling":"node_1_1478122044203"},{"type":"standard","title":null,"output":{},"parent":null,"context":{"amount":"<? @sys-number ?>","payment_reason":"<? input.text.extract('(for|regarding|as).*',0).replaceFirst('^\\S+\\s+', '') ?>"},"metadata":null,"next_step":{"behavior":"jump_to","selector":"condition","dialog_node":"node_2_1478537424848"},"conditions":"#sendMoney && intents[0].confidence > 0.30","description":null,"dialog_node":"node_1_1478537303868","previous_sibling":"node_5_1478122605834"},{"type":"standard","title":null,"output":{"text":{"append":true,"values":["Sure <? $person.fname ?>! Let me know if you have more requests or questions.","Sure! I am here to help with any questions you may have.","Let me know if there is anything else I can help with."],"selection_policy":"sequential"}},"parent":null,"context":null,"metadata":null,"next_step":null,"conditions":"#goodbyes","description":null,"dialog_node":"node_3_1479165321017","previous_sibling":"node_2_1479165281151"},{"type":"standard","title":null,"output":{},"parent":null,"context":{"defaultCounter":"<?$defaultCounter+1?>"},"metadata":null,"next_step":{"behavior":"jump_to","selector":"condition","dialog_node":"node_4_1479165361410"},"conditions":"anything_else","description":null,"dialog_node":"node_2_1478122055040","previous_sibling":"node_7_1479165907920"},{"type":"standard","title":null,"output":{"text":"Alright I will call you <? $alchemy_language.entities.get(0).text ?>"},"parent":null,"context":{"person":{"fname":"<?  $alchemy_language.entities.get(0).text ?>"}},"metadata":null,"next_step":{"behavior":"jump_to","selector":"condition","dialog_node":"node_3_1478122398986"},"conditions":"#callMe && intents[0].confidence>0.96 && $alchemy_language.entities.length>0 && $alchemy_language.entities.get(0).text!=''","description":null,"dialog_node":"node_4_1478301092211","previous_sibling":"node_1_1478720291899"},{"type":"standard","title":null,"output":{},"parent":null,"context":null,"metadata":null,"next_step":{"behavior":"jump_to","selector":"condition","dialog_node":"node_4_1478900017327"},"conditions":"#balance && intents[0].confidence >=0.80","description":null,"dialog_node":"node_1_1478882289339","previous_sibling":"node_9_1478557521266"},{"type":"standard","title":null,"output":{"text":"Sorry I haven't learned answers to questions like this."},"parent":null,"context":null,"metadata":null,"next_step":null,"conditions":"#off_topic","description":null,"dialog_node":"node_7_1479165907920","previous_sibling":"node_3_1479165321017"},{"type":"standard","title":null,"output":{},"parent":null,"context":{"action":{"type":"<? @type ?>","lookup":"transactions","category":"<? @category ?>"}},"metadata":null,"next_step":null,"conditions":"#viewTransactions && intents[0].confidence > 0.50","description":null,"dialog_node":"node_5_1478122605834","previous_sibling":"node_1_1478882289339"},{"type":"standard","title":null,"output":{"text":"Hello! I'm doing good. I'm here to help you. Just say the word."},"parent":null,"context":null,"metadata":null,"next_step":null,"conditions":"#greetings","description":null,"dialog_node":"node_2_1479165281151","previous_sibling":"node_1_1479164501301"},{"type":"standard","title":null,"output":{},"parent":null,"context":{"amount":"<? @sys-number ?>","payment_reason":"<? input.text.extract('(for|regarding|as).*',0).replaceFirst('^\\S+\\s+', '') ?>"},"metadata":null,"next_step":{"behavior":"jump_to","selector":"condition","dialog_node":"node_3_1478720389276"},"conditions":"#receiveMoney && intents[0].confidence > 0.30","description":null,"dialog_node":"node_1_1478720291899","previous_sibling":"node_1_1478537303868"},{"type":"standard","title":null,"output":{"text":"What else can I help you with $person.fname?"},"parent":null,"context":null,"metadata":null,"next_step":null,"conditions":"#cancel && intents[0].confidence>0.70","description":null,"dialog_node":"node_9_1478557521266","previous_sibling":"node_1_1479401108377"},{"type":"standard","title":null,"output":{"text":"I am trained to make payments, request money,  lookup your account balances and help with a review of your payment and transaction history."},"parent":null,"context":null,"metadata":null,"next_step":null,"conditions":"#capabilities","description":null,"dialog_node":"node_1_1479164501301","previous_sibling":"node_4_1478301092211"},{"type":"standard","title":null,"output":{},"parent":null,"context":null,"metadata":null,"next_step":{"behavior":"jump_to","selector":"condition","dialog_node":"node_3_1478122398986"},"conditions":"conversation_start","description":null,"dialog_node":"node_1_1478122044203","previous_sibling":null}],"workspace_id":"d5dce921-d9fc-4178-b647-8a34def055d8","counterexamples":[],"system_settings":null,"learning_opt_out":false}